[ 
  {
    "type": "MIN_CREDITS_AMONG",
    "title": "전공선택 학점",
    "description": "전공선택 40학점 이상 이수",
    "value": 40,
    "targets": [
      {
        "categories": ["ME"],
        "departments": ["MAS"]
      }
    ]
  }, 
  {
    "type": "MIN_COURSES_AMONG",
    "title": "학과 지정 과목",
    "description": "필수 전공선택(선형대수학, 해석학 I, 현대대수학 I, 미분기하학개론, 위상수학, 복소변수함수론, 수리통계학) 중 4과목 이상 이수",
    "value": 4,
    "targets": [
      {
        "codes": ["MAS.20012", "MAS.20041", "MAS.30011", "MAS.30021", "MAS.30031", "MAS.30041", "MAS.30055"]
      }
    ]
  }
]
